handzone/FileUtils.py
handzone/InputStream.py
handzone/PlotModule.py
handzone/SmoothModule.py
handzone/__init__.py
handzone-0.0.12.dist-info/LICENSE
handzone-0.0.12.dist-info/METADATA
handzone-0.0.12.dist-info/WHEEL
handzone-0.0.12.dist-info/top_level.txt
handzone-0.0.12.dist-info/RECORD
