Metadata-Version: 2.1
Name: handzone
Version: 0.0.12
Summary: Hand Utils
Home-page: https://github.com/cavalleria/handzone.git
Author: cavalleria
Author-email: cavallyb@gmail.com
License: MIT
Platform: UNKNOWN
Classifier: Programming Language :: Python :: 3
Classifier: License :: OSI Approved :: MIT License
Classifier: Operating System :: OS Independent
License-File: LICENSE
Requires-Dist: opencv-python
Requires-Dist: numpy
Requires-Dist: scipy
